LICENSE
MANIFEST.in
README.md
setup.py
barrels/__init__.py
barrels/barrel.py
barrels/transforms.py
barrels.egg-info/PKG-INFO
barrels.egg-info/SOURCES.txt
barrels.egg-info/dependency_links.txt
barrels.egg-info/top_level.txt