Metadata-Version: 1.0
Name: barrels
Version: 0.0.6
Summary: Instead of tarballs, barrels of files
Home-page: https://github.com/oskarnyqvists/barrels
Author: oskarnyqvist
Author-email: oskarnyqvist@gmail.com
License: The MIT License (MIT)
